LICENSE
MANIFEST.in
README.rst
setup.py
cmsplugin_nvd3/__init__.py
cmsplugin_nvd3/cms_plugins.py
cmsplugin_nvd3/models.py
cmsplugin_nvd3/settings.py
cmsplugin_nvd3/utils.py
cmsplugin_nvd3.egg-info/PKG-INFO
cmsplugin_nvd3.egg-info/SOURCES.txt
cmsplugin_nvd3.egg-info/dependency_links.txt
cmsplugin_nvd3.egg-info/requires.txt
cmsplugin_nvd3.egg-info/top_level.txt
cmsplugin_nvd3/migrations/0001_initial.py
cmsplugin_nvd3/migrations/0002_rename_plugin_table.py
cmsplugin_nvd3/migrations/__init__.py
cmsplugin_nvd3/south_migrations/0001_initial.py
cmsplugin_nvd3/south_migrations/0002_rename_plugin_table.py
cmsplugin_nvd3/south_migrations/__init__.py
cmsplugin_nvd3/static/nvd3plugin/d3.min.js
cmsplugin_nvd3/static/nvd3plugin/nv.d3.css
cmsplugin_nvd3/static/nvd3plugin/nv.d3.min.js
cmsplugin_nvd3/static/nvd3plugin/nvd3icon.png
cmsplugin_nvd3/templates/cmsplugin_nvd3/nvd3plugin.html