Metadata-Version: 1.1
Name: cmsplugin-nvd3
Version: 0.5.2
Summary: Insert nvd3 charts into django-cms driven websites
Home-page: https://github.com/scidam/cmsplugin-nvd3
Author: Dmitry E. Kislov
Author-email: kislov@easydan.com
License: UNKNOWN
Keywords: nvd3,plugin,charts,nvd3-charts,django,django-cms
Platform: UNKNOWN
Classifier: Development Status :: 4 - Beta
Classifier: Environment :: Web Environment
Classifier: Framework :: Django
Classifier: Framework :: Django :: 1.4
Classifier: Framework :: Django :: 1.5
Classifier: Framework :: Django :: 1.6
Classifier: Framework :: Django :: 1.7
Classifier: Framework :: Django :: 1.8
Classifier: Framework :: Django :: 1.9
Classifier: Intended Audience :: Developers
Classifier: License :: OSI Approved :: MIT License
Classifier: Operating System :: OS Independent
Classifier: Programming Language :: Python
Classifier: Programming Language :: Python :: 2.7
Classifier: Programming Language :: Python :: 3.3
Classifier: Programming Language :: Python :: 3.4
Classifier: Programming Language :: Python :: 3.5
Classifier: Topic :: Internet :: WWW/HTTP :: Dynamic Content
Classifier: Topic :: Internet :: WWW/HTTP :: Site Management
Classifier: Topic :: Multimedia :: Graphics :: Presentation
